{
"type": "FeatureCollection",
"name": "Reg_vertical_circulation",
"crs": { "type": "name", "properties": { "name": "urn:ogc:def:crs:OGC:1.3:CRS84" } },
"features": [
{ "type": "Feature", "properties": { "feature_id": "access_door_l2", "name": "Door", "level": "2" }, "geometry": { "type": "Point", "coordinates": [ -118.394302309436526, 33.941789211633655 ] } }
]
}
